cpcv/__init__.py
cpcv/cpcv.py
cpcv-0.1.0.dist-info/licenses/LICENSE
cpcv-0.1.0.dist-info/METADATA
cpcv-0.1.0.dist-info/WHEEL
cpcv-0.1.0.dist-info/top_level.txt
cpcv-0.1.0.dist-info/RECORD
