Metadata-Version: 2.4
Name: cpcv
Version: 0.1.0
Summary: CPCV with Embargo for financial train-test splitting
Home-page: https://github.com/Yosri-Ben-Halima/cpcv
Author: Yosri Ben Halima
Author-email: yosri.benhalima@ept.ucar.tn
Classifier: Development Status :: 3 - Alpha
Classifier: Intended Audience :: Science/Research
Classifier: Intended Audience :: Financial and Insurance Industry
Classifier: License :: OSI Approved :: MIT License
Classifier: Programming Language :: Python :: 3
Classifier: Topic :: Scientific/Engineering
Classifier: Topic :: Office/Business :: Financial :: Investment
Requires-Python: >=3.8
License-File: LICENSE
Requires-Dist: numpy>=1.21
Requires-Dist: pandas>=1.5
Requires-Dist: scikit-learn>=1.0
Dynamic: author
Dynamic: author-email
Dynamic: classifier
Dynamic: description
Dynamic: description-content-type
Dynamic: home-page
Dynamic: license-file
Dynamic: requires-dist
Dynamic: requires-python
Dynamic: summary
